kuro/__init__.py
kuro/protocol.py
python_kuro-0.0.44.dist-info/LICENSE
python_kuro-0.0.44.dist-info/METADATA
python_kuro-0.0.44.dist-info/WHEEL
python_kuro-0.0.44.dist-info/top_level.txt
python_kuro-0.0.44.dist-info/RECORD
