Metadata-Version: 2.1
Name: python-kuro
Version: 0.0.44
Summary: 'Python library for interfacing with Pioneer Kuro TV using the serial port',  # Required
Home-page: https://github.com/gpulido/python-kuro
Author: Gabriel Pulido
Author-email: gabriel.pulidodetorres@gmail.com
License: MIT
Keywords: kuro,pioneer,tv,serial
Platform: UNKNOWN
Classifier: Development Status :: 3 - Alpha
Classifier: Intended Audience :: Developers
Classifier: Topic :: Software Development :: Build Tools
Classifier: License :: OSI Approved :: MIT License
Classifier: Programming Language :: Python :: 3
Classifier: Programming Language :: Python :: 3.4
Classifier: Programming Language :: Python :: 3.5
Classifier: Programming Language :: Python :: 3.6
Classifier: Programming Language :: Python :: 3.7
Classifier: Programming Language :: Python :: 3.8
Classifier: Programming Language :: Python :: 3.9
License-File: LICENSE
Requires-Dist: pySerial
